{
    "price": {
        "current": {
            "datetime": "2022-12-22 00:00:00",
            "count": 125.0,
            "mean": 758.4,
            "std": 51.17017780674788,
            "min": 450.0,
            "25%": 780.0,
            "50%": 780.0,
            "75%": 780.0,
            "max": 800.0
        },
        "summary7Days": {
            "datetime": "2022-12-22 00:00:00",
            "count": 3.0,
            "mean": -0.6983606557377016,
            "std": 2.28163703513205,
            "min": -50.0,
            "25%": 0.0,
            "50%": 0.0,
            "75%": 0.0,
            "max": 0.0
        },
        "volatility": {
            "weekly": {
                "min": {
                    "basePrice": 500.0,
                    "latestPrice": 450.0,
                    "percent": -10.0
                },
                "50%": {
                    "basePrice": 780.0,
                    "latestPrice": 780.0,
                    "percent": 0.0
                }
            },
            "daily": {
                "min": {
                    "basePrice": 450.0,
                    "latestPrice": 450.0,
                    "percent": 0.0
                },
                "50%": {
                    "basePrice": 780.0,
                    "latestPrice": 780.0,
                    "percent": 0.0
                }
            }
        },
        "weekly": {
            "archive": {
                "count": 7,
                "data": [
                    {
                        "datetime": "2022-12-16 00:00:00",
                        "count": 122.0,
                        "mean": 759.0983606557377,
                        "std": 48.88854077161583,
                        "min": 500.0,
                        "25%": 780.0,
                        "50%": 780.0,
                        "75%": 780.0,
                        "max": 800.0
                    },
                    {
                        "datetime": "2022-12-17 00:00:00",
                        "count": 122.0,
                        "mean": 759.0983606557377,
                        "std": 48.88854077161583,
                        "min": 500.0,
                        "25%": 780.0,
                        "50%": 780.0,
                        "75%": 780.0,
                        "max": 800.0
                    },
                    {
                        "datetime": "2022-12-18 00:00:00",
                        "count": 122.0,
                        "mean": 759.0983606557377,
                        "std": 48.88854077161583,
                        "min": 500.0,
                        "25%": 780.0,
                        "50%": 780.0,
                        "75%": 780.0,
                        "max": 800.0
                    },
                    {
                        "datetime": "2022-12-19 00:00:00",
                        "count": 122.0,
                        "mean": 758.688524590164,
                        "std": 51.23194412309201,
                        "min": 450.0,
                        "25%": 780.0,
                        "50%": 780.0,
                        "75%": 780.0,
                        "max": 800.0
                    },
                    {
                        "datetime": "2022-12-20 00:00:00",
                        "count": 122.0,
                        "mean": 758.688524590164,
                        "std": 51.23194412309201,
                        "min": 450.0,
                        "25%": 780.0,
                        "50%": 780.0,
                        "75%": 780.0,
                        "max": 800.0
                    },
                    {
                        "datetime": "2022-12-21 00:00:00",
                        "count": 124.0,
                        "mean": 759.0322580645161,
                        "std": 50.885162512911194,
                        "min": 450.0,
                        "25%": 780.0,
                        "50%": 780.0,
                        "75%": 780.0,
                        "max": 800.0
                    },
                    {
                        "datetime": "2022-12-22 00:00:00",
                        "count": 125.0,
                        "mean": 758.4,
                        "std": 51.17017780674788,
                        "min": 450.0,
                        "25%": 780.0,
                        "50%": 780.0,
                        "75%": 780.0,
                        "max": 800.0
                    }
                ]
            },
            "diff": {
                "count": 7,
                "data": [
                    {
                        "datetime": "2022-12-16 00:00:00",
                        "count": null,
                        "mean": null,
                        "std": null,
                        "min": null,
                        "25%": null,
                        "50%": null,
                        "75%": null,
                        "max": null
                    },
                    {
                        "datetime": "2022-12-17 00:00:00",
                        "count": 0.0,
                        "mean": 0.0,
                        "std": 0.0,
                        "min": 0.0,
                        "25%": 0.0,
                        "50%": 0.0,
                        "75%": 0.0,
                        "max": 0.0
                    },
                    {
                        "datetime": "2022-12-18 00:00:00",
                        "count": 0.0,
                        "mean": 0.0,
                        "std": 0.0,
                        "min": 0.0,
                        "25%": 0.0,
                        "50%": 0.0,
                        "75%": 0.0,
                        "max": 0.0
                    },
                    {
                        "datetime": "2022-12-19 00:00:00",
                        "count": 0.0,
                        "mean": -0.40983606557369967,
                        "std": 2.3434033514761836,
                        "min": -50.0,
                        "25%": 0.0,
                        "50%": 0.0,
                        "75%": 0.0,
                        "max": 0.0
                    },
                    {
                        "datetime": "2022-12-20 00:00:00",
                        "count": 0.0,
                        "mean": 0.0,
                        "std": 0.0,
                        "min": 0.0,
                        "25%": 0.0,
                        "50%": 0.0,
                        "75%": 0.0,
                        "max": 0.0
                    },
                    {
                        "datetime": "2022-12-21 00:00:00",
                        "count": 2.0,
                        "mean": 0.34373347435212054,
                        "std": -0.34678161018081965,
                        "min": 0.0,
                        "25%": 0.0,
                        "50%": 0.0,
                        "75%": 0.0,
                        "max": 0.0
                    },
                    {
                        "datetime": "2022-12-22 00:00:00",
                        "count": 1.0,
                        "mean": -0.6322580645161224,
                        "std": 0.2850152938366861,
                        "min": 0.0,
                        "25%": 0.0,
                        "50%": 0.0,
                        "75%": 0.0,
                        "max": 0.0
                    }
                ]
            }
        },
        "halfYear": {
            "archive": {
                "count": 13,
                "data": [
                    {
                        "datetime": "2022-07-07 00:00:00",
                        "count": 0.0,
                        "mean": 0.0,
                        "std": 0.0,
                        "min": 0.0,
                        "25%": 0.0,
                        "50%": 0.0,
                        "75%": 0.0,
                        "max": 0.0
                    },
                    {
                        "datetime": "2022-07-21 00:00:00",
                        "count": 0.0,
                        "mean": 0.0,
                        "std": 0.0,
                        "min": 0.0,
                        "25%": 0.0,
                        "50%": 0.0,
                        "75%": 0.0,
                        "max": 0.0
                    },
                    {
                        "datetime": "2022-08-04 00:00:00",
                        "count": 0.0,
                        "mean": 0.0,
                        "std": 0.0,
                        "min": 0.0,
                        "25%": 0.0,
                        "50%": 0.0,
                        "75%": 0.0,
                        "max": 0.0
                    },
                    {
                        "datetime": "2022-08-18 00:00:00",
                        "count": 84.0,
                        "mean": 696.4285714285714,
                        "std": 23.00564923512867,
                        "min": 550.0,
                        "25%": 700.0,
                        "50%": 700.0,
                        "75%": 700.0,
                        "max": 700.0
                    },
                    {
                        "datetime": "2022-09-01 00:00:00",
                        "count": 85.0,
                        "mean": 582.4705882352941,
                        "std": 18.63853422303356,
                        "min": 550.0,
                        "25%": 580.0,
                        "50%": 580.0,
                        "75%": 580.0,
                        "max": 700.0
                    },
                    {
                        "datetime": "2022-09-15 00:00:00",
                        "count": 57.0,
                        "mean": 587.8947368421053,
                        "std": 31.324160124715185,
                        "min": 550.0,
                        "25%": 580.0,
                        "50%": 580.0,
                        "75%": 580.0,
                        "max": 700.0
                    },
                    {
                        "datetime": "2022-09-29 00:00:00",
                        "count": 37.0,
                        "mean": 573.7837837837837,
                        "std": 23.25598505419284,
                        "min": 480.0,
                        "25%": 580.0,
                        "50%": 580.0,
                        "75%": 580.0,
                        "max": 580.0
                    },
                    {
                        "datetime": "2022-10-13 00:00:00",
                        "count": 20.0,
                        "mean": 608.5,
                        "std": 54.60624602793309,
                        "min": 550.0,
                        "25%": 580.0,
                        "50%": 580.0,
                        "75%": 610.0,
                        "max": 700.0
                    },
                    {
                        "datetime": "2022-10-27 00:00:00",
                        "count": 14.0,
                        "mean": 706.4285714285714,
                        "std": 61.470085639857615,
                        "min": 550.0,
                        "25%": 680.0,
                        "50%": 700.0,
                        "75%": 760.0,
                        "max": 780.0
                    },
                    {
                        "datetime": "2022-11-10 00:00:00",
                        "count": 19.0,
                        "mean": 667.8947368421053,
                        "std": 55.83496986342092,
                        "min": 550.0,
                        "25%": 680.0,
                        "50%": 680.0,
                        "75%": 700.0,
                        "max": 780.0
                    },
                    {
                        "datetime": "2022-11-24 00:00:00",
                        "count": 75.0,
                        "mean": 758.8,
                        "std": 55.38465003463919,
                        "min": 550.0,
                        "25%": 780.0,
                        "50%": 780.0,
                        "75%": 780.0,
                        "max": 800.0
                    },
                    {
                        "datetime": "2022-12-08 00:00:00",
                        "count": 85.0,
                        "mean": 749.4117647058823,
                        "std": 66.14113591362019,
                        "min": 480.0,
                        "25%": 780.0,
                        "50%": 780.0,
                        "75%": 780.0,
                        "max": 800.0
                    },
                    {
                        "datetime": "2022-12-22 00:00:00",
                        "count": 125.0,
                        "mean": 758.4,
                        "std": 51.17017780674788,
                        "min": 450.0,
                        "25%": 780.0,
                        "50%": 780.0,
                        "75%": 780.0,
                        "max": 800.0
                    }
                ]
            },
            "diff": {
                "count": 13,
                "data": [
                    {
                        "datetime": "2022-07-07 00:00:00",
                        "count": null,
                        "mean": null,
                        "std": null,
                        "min": null,
                        "25%": null,
                        "50%": null,
                        "75%": null,
                        "max": null
                    },
                    {
                        "datetime": "2022-07-21 00:00:00",
                        "count": 0.0,
                        "mean": 0.0,
                        "std": 0.0,
                        "min": 0.0,
                        "25%": 0.0,
                        "50%": 0.0,
                        "75%": 0.0,
                        "max": 0.0
                    },
                    {
                        "datetime": "2022-08-04 00:00:00",
                        "count": 0.0,
                        "mean": 0.0,
                        "std": 0.0,
                        "min": 0.0,
                        "25%": 0.0,
                        "50%": 0.0,
                        "75%": 0.0,
                        "max": 0.0
                    },
                    {
                        "datetime": "2022-08-18 00:00:00",
                        "count": 84.0,
                        "mean": 696.4285714285714,
                        "std": 23.00564923512867,
                        "min": 550.0,
                        "25%": 700.0,
                        "50%": 700.0,
                        "75%": 700.0,
                        "max": 700.0
                    },
                    {
                        "datetime": "2022-09-01 00:00:00",
                        "count": 1.0,
                        "mean": -113.9579831932773,
                        "std": -4.367115012095109,
                        "min": 0.0,
                        "25%": -120.0,
                        "50%": -120.0,
                        "75%": -120.0,
                        "max": 0.0
                    },
                    {
                        "datetime": "2022-09-15 00:00:00",
                        "count": -28.0,
                        "mean": 5.424148606811173,
                        "std": 12.685625901681625,
                        "min": 0.0,
                        "25%": 0.0,
                        "50%": 0.0,
                        "75%": 0.0,
                        "max": 0.0
                    },
                    {
                        "datetime": "2022-09-29 00:00:00",
                        "count": -20.0,
                        "mean": -14.11095305832157,
                        "std": -8.068175070522344,
                        "min": -70.0,
                        "25%": 0.0,
                        "50%": 0.0,
                        "75%": 0.0,
                        "max": -120.0
                    },
                    {
                        "datetime": "2022-10-13 00:00:00",
                        "count": -17.0,
                        "mean": 34.71621621621625,
                        "std": 31.350260973740248,
                        "min": 70.0,
                        "25%": 0.0,
                        "50%": 0.0,
                        "75%": 30.0,
                        "max": 120.0
                    },
                    {
                        "datetime": "2022-10-27 00:00:00",
                        "count": -6.0,
                        "mean": 97.92857142857144,
                        "std": 6.863839611924526,
                        "min": 0.0,
                        "25%": 100.0,
                        "50%": 120.0,
                        "75%": 150.0,
                        "max": 80.0
                    },
                    {
                        "datetime": "2022-11-10 00:00:00",
                        "count": 5.0,
                        "mean": -38.53383458646613,
                        "std": -5.635115776436692,
                        "min": 0.0,
                        "25%": 0.0,
                        "50%": -20.0,
                        "75%": -60.0,
                        "max": 0.0
                    },
                    {
                        "datetime": "2022-11-24 00:00:00",
                        "count": 56.0,
                        "mean": 90.90526315789464,
                        "std": -0.4503198287817298,
                        "min": 0.0,
                        "25%": 100.0,
                        "50%": 100.0,
                        "75%": 80.0,
                        "max": 20.0
                    },
                    {
                        "datetime": "2022-12-08 00:00:00",
                        "count": 10.0,
                        "mean": -9.388235294117635,
                        "std": 10.756485878980996,
                        "min": -70.0,
                        "25%": 0.0,
                        "50%": 0.0,
                        "75%": 0.0,
                        "max": 0.0
                    },
                    {
                        "datetime": "2022-12-22 00:00:00",
                        "count": 40.0,
                        "mean": 8.988235294117658,
                        "std": -14.97095810687231,
                        "min": -30.0,
                        "25%": 0.0,
                        "50%": 0.0,
                        "75%": 0.0,
                        "max": 0.0
                    }
                ]
            }
        },
        "OneYear": {
            "archive": {
                "count": 0,
                "data": []
            },
            "diff": {
                "count": 0,
                "data": []
            }
        }
    },
    "calc": {
        "latest_date": "2022-12-22 00:00:00",
        "updated_at": "2022-12-22 20:08:43"
    }
}