{
    "price": {
        "current": {
            "datetime": "2022-11-03 00:00:00",
            "count": 130.0,
            "mean": 50.55384615384615,
            "std": 5.688369118821479,
            "min": 42.0,
            "25%": 50.0,
            "50%": 50.0,
            "75%": 50.0,
            "max": 100.0
        },
        "summary7Days": {
            "datetime": "2022-11-03 00:00:00",
            "count": -97.0,
            "mean": -8.767739749237549,
            "std": -8.36707171178961,
            "min": 0.0,
            "25%": 0.0,
            "50%": 0.0,
            "75%": -30.0,
            "max": 20.0
        },
        "volatility": {
            "weekly": {
                "min": {
                    "basePrice": 42.0,
                    "latestPrice": 42.0,
                    "percent": 0.0
                },
                "50%": {
                    "basePrice": 50.0,
                    "latestPrice": 50.0,
                    "percent": 0.0
                }
            },
            "daily": {
                "min": {
                    "basePrice": 42.0,
                    "latestPrice": 42.0,
                    "percent": 0.0
                },
                "50%": {
                    "basePrice": 50.0,
                    "latestPrice": 50.0,
                    "percent": 0.0
                }
            }
        },
        "weekly": {
            "archive": {
                "count": 7,
                "data": [
                    {
                        "datetime": "2022-10-28 00:00:00",
                        "count": 227.0,
                        "mean": 59.3215859030837,
                        "std": 14.055440830611088,
                        "min": 42.0,
                        "25%": 50.0,
                        "50%": 50.0,
                        "75%": 80.0,
                        "max": 80.0
                    },
                    {
                        "datetime": "2022-10-29 00:00:00",
                        "count": 208.0,
                        "mean": 58.32692307692308,
                        "std": 13.654071472696115,
                        "min": 42.0,
                        "25%": 50.0,
                        "50%": 50.0,
                        "75%": 80.0,
                        "max": 80.0
                    },
                    {
                        "datetime": "2022-10-30 00:00:00",
                        "count": 197.0,
                        "mean": 56.6497461928934,
                        "std": 13.64992944724789,
                        "min": 27.0,
                        "25%": 50.0,
                        "50%": 50.0,
                        "75%": 50.0,
                        "max": 80.0
                    },
                    {
                        "datetime": "2022-10-31 00:00:00",
                        "count": 174.0,
                        "mean": 54.88505747126437,
                        "std": 12.78494896113686,
                        "min": 27.0,
                        "25%": 50.0,
                        "50%": 50.0,
                        "75%": 50.0,
                        "max": 100.0
                    },
                    {
                        "datetime": "2022-11-01 00:00:00",
                        "count": 155.0,
                        "mean": 52.96774193548387,
                        "std": 11.213639280224603,
                        "min": 27.0,
                        "25%": 50.0,
                        "50%": 50.0,
                        "75%": 50.0,
                        "max": 100.0
                    },
                    {
                        "datetime": "2022-11-02 00:00:00",
                        "count": 130.0,
                        "mean": 50.55384615384615,
                        "std": 5.688369118821479,
                        "min": 42.0,
                        "25%": 50.0,
                        "50%": 50.0,
                        "75%": 50.0,
                        "max": 100.0
                    },
                    {
                        "datetime": "2022-11-03 00:00:00",
                        "count": 130.0,
                        "mean": 50.55384615384615,
                        "std": 5.688369118821479,
                        "min": 42.0,
                        "25%": 50.0,
                        "50%": 50.0,
                        "75%": 50.0,
                        "max": 100.0
                    }
                ]
            },
            "diff": {
                "count": 7,
                "data": [
                    {
                        "datetime": "2022-10-28 00:00:00",
                        "count": null,
                        "mean": null,
                        "std": null,
                        "min": null,
                        "25%": null,
                        "50%": null,
                        "75%": null,
                        "max": null
                    },
                    {
                        "datetime": "2022-10-29 00:00:00",
                        "count": -19.0,
                        "mean": -0.9946628261606207,
                        "std": -0.4013693579149731,
                        "min": 0.0,
                        "25%": 0.0,
                        "50%": 0.0,
                        "75%": 0.0,
                        "max": 0.0
                    },
                    {
                        "datetime": "2022-10-30 00:00:00",
                        "count": -11.0,
                        "mean": -1.6771768840296772,
                        "std": -0.004142025448224729,
                        "min": -15.0,
                        "25%": 0.0,
                        "50%": 0.0,
                        "75%": -30.0,
                        "max": 0.0
                    },
                    {
                        "datetime": "2022-10-31 00:00:00",
                        "count": -23.0,
                        "mean": -1.7646887216290352,
                        "std": -0.8649804861110297,
                        "min": 0.0,
                        "25%": 0.0,
                        "50%": 0.0,
                        "75%": 0.0,
                        "max": 20.0
                    },
                    {
                        "datetime": "2022-11-01 00:00:00",
                        "count": -19.0,
                        "mean": -1.9173155357804958,
                        "std": -1.5713096809122575,
                        "min": 0.0,
                        "25%": 0.0,
                        "50%": 0.0,
                        "75%": 0.0,
                        "max": 0.0
                    },
                    {
                        "datetime": "2022-11-02 00:00:00",
                        "count": -25.0,
                        "mean": -2.41389578163772,
                        "std": -5.5252701614031245,
                        "min": 15.0,
                        "25%": 0.0,
                        "50%": 0.0,
                        "75%": 0.0,
                        "max": 0.0
                    },
                    {
                        "datetime": "2022-11-03 00:00:00",
                        "count": 0.0,
                        "mean": 0.0,
                        "std": 0.0,
                        "min": 0.0,
                        "25%": 0.0,
                        "50%": 0.0,
                        "75%": 0.0,
                        "max": 0.0
                    }
                ]
            }
        },
        "halfYear": {
            "archive": {
                "count": 7,
                "data": [
                    {
                        "datetime": "2022-08-08 00:00:00",
                        "count": 0.0,
                        "mean": 58.74060822898032,
                        "std": 30.07175970123857,
                        "min": 50.0,
                        "25%": 50.0,
                        "50%": 50.0,
                        "75%": 77.0,
                        "max": 700.0
                    },
                    {
                        "datetime": "2022-08-22 00:00:00",
                        "count": 518.0,
                        "mean": 56.2027027027027,
                        "std": 29.01476034078023,
                        "min": 33.0,
                        "25%": 50.0,
                        "50%": 50.0,
                        "75%": 50.0,
                        "max": 650.0
                    },
                    {
                        "datetime": "2022-09-05 00:00:00",
                        "count": 742.0,
                        "mean": 63.76010781671159,
                        "std": 15.706024837071023,
                        "min": 33.0,
                        "25%": 50.0,
                        "50%": 50.0,
                        "75%": 80.0,
                        "max": 100.0
                    },
                    {
                        "datetime": "2022-09-19 00:00:00",
                        "count": 371.0,
                        "mean": 55.03234501347709,
                        "std": 12.650992040989692,
                        "min": 33.0,
                        "25%": 50.0,
                        "50%": 50.0,
                        "75%": 50.0,
                        "max": 100.0
                    },
                    {
                        "datetime": "2022-10-03 00:00:00",
                        "count": 270.0,
                        "mean": 51.5,
                        "std": 6.916254223978925,
                        "min": 42.0,
                        "25%": 50.0,
                        "50%": 50.0,
                        "75%": 50.0,
                        "max": 100.0
                    },
                    {
                        "datetime": "2022-10-17 00:00:00",
                        "count": 430.0,
                        "mean": 64.42790697674418,
                        "std": 15.127836389830517,
                        "min": 42.0,
                        "25%": 50.0,
                        "50%": 50.0,
                        "75%": 80.0,
                        "max": 100.0
                    },
                    {
                        "datetime": "2022-10-31 00:00:00",
                        "count": 174.0,
                        "mean": 54.88505747126437,
                        "std": 12.78494896113686,
                        "min": 27.0,
                        "25%": 50.0,
                        "50%": 50.0,
                        "75%": 50.0,
                        "max": 100.0
                    }
                ]
            },
            "diff": {
                "count": 7,
                "data": [
                    {
                        "datetime": "2022-08-08 00:00:00",
                        "count": null,
                        "mean": null,
                        "std": null,
                        "min": null,
                        "25%": null,
                        "50%": null,
                        "75%": null,
                        "max": null
                    },
                    {
                        "datetime": "2022-08-22 00:00:00",
                        "count": 518.0,
                        "mean": -2.537905526277619,
                        "std": -1.056999360458338,
                        "min": -17.0,
                        "25%": 0.0,
                        "50%": 0.0,
                        "75%": -27.0,
                        "max": -50.0
                    },
                    {
                        "datetime": "2022-09-05 00:00:00",
                        "count": 224.0,
                        "mean": 7.557405114008887,
                        "std": -13.308735503709208,
                        "min": 0.0,
                        "25%": 0.0,
                        "50%": 0.0,
                        "75%": 30.0,
                        "max": -550.0
                    },
                    {
                        "datetime": "2022-09-19 00:00:00",
                        "count": -371.0,
                        "mean": -8.727762803234498,
                        "std": -3.0550327960813313,
                        "min": 0.0,
                        "25%": 0.0,
                        "50%": 0.0,
                        "75%": -30.0,
                        "max": 0.0
                    },
                    {
                        "datetime": "2022-10-03 00:00:00",
                        "count": -101.0,
                        "mean": -3.532345013477091,
                        "std": -5.7347378170107675,
                        "min": 9.0,
                        "25%": 0.0,
                        "50%": 0.0,
                        "75%": 0.0,
                        "max": 0.0
                    },
                    {
                        "datetime": "2022-10-17 00:00:00",
                        "count": 160.0,
                        "mean": 12.927906976744183,
                        "std": 8.211582165851592,
                        "min": 0.0,
                        "25%": 0.0,
                        "50%": 0.0,
                        "75%": 30.0,
                        "max": 0.0
                    },
                    {
                        "datetime": "2022-10-31 00:00:00",
                        "count": -256.0,
                        "mean": -9.542849505479815,
                        "std": -2.342887428693656,
                        "min": -15.0,
                        "25%": 0.0,
                        "50%": 0.0,
                        "75%": -30.0,
                        "max": 0.0
                    }
                ]
            }
        },
        "OneYear": {
            "archive": {
                "count": 0,
                "data": []
            },
            "diff": {
                "count": 0,
                "data": []
            }
        }
    },
    "calc": {
        "latest_date": "2022-11-03 00:00:00",
        "updated_at": "2022-11-03 21:30:06"
    }
}